realtimex_computer_use/__init__.py
realtimex_computer_use/__main__.py
realtimex_computer_use/server.py
realtimex_computer_use/tools/__init__.py
realtimex_computer_use/tools/app_launcher.py
realtimex_computer_use/tools/browser.py
realtimex_computer_use/tools/credential_typing.py
realtimex_computer_use/tools/credentials.py
realtimex_computer_use-1.4.0.dist-info/METADATA
realtimex_computer_use-1.4.0.dist-info/WHEEL
realtimex_computer_use-1.4.0.dist-info/entry_points.txt
realtimex_computer_use-1.4.0.dist-info/RECORD
