Metadata-Version: 2.4
Name: realtimex-computer-use
Version: 1.4.0
Summary: MCP server providing computer control tools for AI agents
Author-email: RTA <rta@example.com>
License: Proprietary
Keywords: automation,browser,computer-use,mcp
Classifier: Development Status :: 4 - Beta
Classifier: Intended Audience :: Developers
Classifier: Programming Language :: Python :: 3
Classifier: Programming Language :: Python :: 3.11
Classifier: Programming Language :: Python :: 3.12
Requires-Python: >=3.11
Requires-Dist: fastmcp>=2.13.0.2
Requires-Dist: httpx>=0.28.1
Requires-Dist: pyautogui>=0.9.54
Requires-Dist: realtimex-toolkit>=1.2.0
